physical_sources-0.7.10.dist-info/METADATA
physical_sources-0.7.10.dist-info/WHEEL
physical_sources-0.7.10.dist-info/licenses/LICENSE.txt
physical_sources/__init__.py
physical_sources/acoustic/__init__.py
physical_sources/acoustic/analytic_source.py
physical_sources/acoustic/grid_sphere_source.py
physical_sources/acoustic/inoisesource.py
physical_sources/acoustic/point_source.py
physical_sources/acoustic/source_definitions/__init__.py
physical_sources/acoustic/source_definitions/noisefile.py
physical_sources/acoustic/sphere_source.py
physical_sources-0.7.10.dist-info/RECORD
